wildlife_datasets/__init__.py
wildlife_datasets/analysis/__init__.py
wildlife_datasets/analysis/statistics.py
wildlife_datasets/datasets/__init__.py
wildlife_datasets/datasets/aau_zebrafish.py
wildlife_datasets/datasets/aerial_cattle.py
wildlife_datasets/datasets/amvrakikos_turtles.py
wildlife_datasets/datasets/animal_clef.py
wildlife_datasets/datasets/atrw.py
wildlife_datasets/datasets/balearic_lizard.py
wildlife_datasets/datasets/beluga_id.py
wildlife_datasets/datasets/bird_individual_id.py
wildlife_datasets/datasets/bristol_gorillas_2020.py
wildlife_datasets/datasets/cat_individual_images.py
wildlife_datasets/datasets/cattle_muzzle.py
wildlife_datasets/datasets/chicks4free_id.py
wildlife_datasets/datasets/cobra_re_identification_youngstock.py
wildlife_datasets/datasets/cow_dataset.py
wildlife_datasets/datasets/cows.py
wildlife_datasets/datasets/ctai.py
wildlife_datasets/datasets/czechlynx.py
wildlife_datasets/datasets/czoo.py
wildlife_datasets/datasets/datasets.py
wildlife_datasets/datasets/datasets_wildme.py
wildlife_datasets/datasets/dog_face_net.py
wildlife_datasets/datasets/downloads.py
wildlife_datasets/datasets/drosophila.py
wildlife_datasets/datasets/elpephants.py
wildlife_datasets/datasets/friesian_cattle.py
wildlife_datasets/datasets/giraffe_zebra_id.py
wildlife_datasets/datasets/giraffes.py
wildlife_datasets/datasets/happy_whale.py
wildlife_datasets/datasets/holstein_cattle_recognition.py
wildlife_datasets/datasets/humpback_whale_id.py
wildlife_datasets/datasets/hyena_id.py
wildlife_datasets/datasets/ipanda.py
wildlife_datasets/datasets/leopard_id.py
wildlife_datasets/datasets/lion_data.py
wildlife_datasets/datasets/macaque_faces.py
wildlife_datasets/datasets/mpdd.py
wildlife_datasets/datasets/multi_cam_cows.py
wildlife_datasets/datasets/ndd.py
wildlife_datasets/datasets/noaa_right_whale.py
wildlife_datasets/datasets/nyala_data.py
wildlife_datasets/datasets/open_cows.py
wildlife_datasets/datasets/polar_bear_vid_id.py
wildlife_datasets-1.0.8.dist-info/licenses/LICENSE
wildlife_datasets-1.0.8.dist-info/METADATA
wildlife_datasets-1.0.8.dist-info/WHEEL
wildlife_datasets-1.0.8.dist-info/top_level.txt
wildlife_datasets-1.0.8.dist-info/RECORD
