Metadata-Version: 2.4
Name: wildlife-datasets
Version: 1.0.8
Summary: Library for easier access and research of wildlife re-identification datasets
Author-email: Lukáš Adam <lukas.adam.cr@gmail.com>, Vojtěch Čermák <cermak.vojtech@seznam.cz>
Maintainer-email: Lukáš Adam <lukas.adam.cr@gmail.com>, Vojtěch Čermák <cermak.vojtech@seznam.cz>
License-Expression: MIT
Project-URL: Homepage, https://github.com/WildlifeDatasets/wildlife-datasets
Project-URL: Documentation, https://wildlifedatasets.github.io/wildlife-datasets/
Project-URL: Bug Tracker, https://github.com/WildlifeDatasets/wildlife-datasets/issues
Keywords: wildlife,re-identification,datasets
Classifier: Programming Language :: Python :: 3
Classifier: Operating System :: OS Independent
Requires-Python: >=3.8
License-File: LICENSE
Requires-Dist: numpy>=1.19.4
Requires-Dist: pandas>=1.1.4
Requires-Dist: tqdm>=4.62.3
Requires-Dist: opencv-python>=4.5.5.62
Requires-Dist: Pillow>=7.1.2
Requires-Dist: scikit-learn>=1.0.1
Requires-Dist: matplotlib>=3.5.1
Requires-Dist: pycocotools>=2.0.1
Requires-Dist: datasets
Requires-Dist: gdown
Requires-Dist: kaggle
Requires-Dist: pyinaturalist
Dynamic: license-file
